chemistry_and_robots/__init__.py
chemistry_and_robots/data_model/__init__.py
chemistry_and_robots/data_model/base_ontology.py
chemistry_and_robots/data_model/iris.py
chemistry_and_robots/data_model/ontobpr.py
chemistry_and_robots/data_model/ontodoe.py
chemistry_and_robots/data_model/ontohplc.py
chemistry_and_robots/data_model/ontolab.py
chemistry_and_robots/data_model/ontoreaction.py
chemistry_and_robots/data_model/ontovapourtec.py
chemistry_and_robots/data_model/unit_conversion.py
chemistry_and_robots/hardware/__init__.py
chemistry_and_robots/hardware/hplc.py
chemistry_and_robots/kg_operations/__init__.py
chemistry_and_robots/kg_operations/dict_and_list.py
chemistry_and_robots/kg_operations/sparql_client.py
chemistry_and_robots/resources/__init__.py
chemistry_and_robots/resources/ontoagent/Service__DoE.ttl
chemistry_and_robots/resources/ontoagent/Service__Execution.ttl
chemistry_and_robots/resources/ontoagent/Service__PostProc.ttl
chemistry_and_robots/resources/ontology/OntoDoE.owl
chemistry_and_robots/resources/ontology/OntoGoal.owl
chemistry_and_robots/resources/ontology/OntoHPLC.owl
chemistry_and_robots/resources/ontology/OntoLab.owl
chemistry_and_robots/resources/ontology/OntoReaction.owl
chemistry_and_robots/resources/ontology/OntoVapourtec.owl
chemistry_and_robots/resources/sample_data/doe.ttl
chemistry_and_robots/resources/sample_data/doe_no_prior_data.ttl
chemistry_and_robots/resources/sample_data/doe_template.ttl
chemistry_and_robots/resources/sample_data/dummy_lab.ttl
chemistry_and_robots/resources/sample_data/dummy_post_proc.ttl
chemistry_and_robots/resources/sample_data/new_exp_data.ttl
chemistry_and_robots/resources/sample_data/new_exp_data_out_of_range.ttl
chemistry_and_robots/resources/sample_data/raw_hplc_report_txt.txt
chemistry_and_robots/resources/sample_data/raw_hplc_report_txt_incomplete.txt
chemistry_and_robots/resources/sample_data/raw_hplc_report_txt_no_product.txt
chemistry_and_robots-1.6.2.dist-info/METADATA
chemistry_and_robots-1.6.2.dist-info/WHEEL
chemistry_and_robots-1.6.2.dist-info/top_level.txt
chemistry_and_robots-1.6.2.dist-info/RECORD
