Metadata-Version: 2.1
Name: chemistry-and-robots
Version: 1.6.2
Summary: chemistryandrobots contains dataclasses and sparql queries for concepts related to chemistry_and_robots as part of The World Avatar project.
Home-page: https://github.com/cambridge-cares/TheWorldAvatar/tree/main/Agents/utils/chemistry_and_robots
Author: Jiaru Bai
Author-email: jb2197@cam.ac.uk
License: MIT
Requires-Python: >=3.8
Requires-Dist: pyderivationagent (>=1.4.1)
Requires-Dist: pydantic (==1.9.0)
Requires-Dist: pandas
Requires-Dist: xlrd
Requires-Dist: xlwt
Provides-Extra: dev
Requires-Dist: testcontainers (>=3.4.2) ; extra == 'dev'
Requires-Dist: pytest (>=6.2.3) ; extra == 'dev'
Requires-Dist: pytest-docker-compose (>=3.2.1) ; extra == 'dev'
Requires-Dist: pytest-rerunfailures (>=10.2) ; extra == 'dev'
